Metadata-Version: 2.1
Name: tacle
Version: 1.2.2
Summary: TaCLe is a tool for learning constraints and formulas in spreadsheets.
Home-page: https://github.com/ML-KULeuven/tacle
Author: Samuel Kolb
Author-email: samuel.kolb@me.com
License: MIT
Platform: UNKNOWN
Classifier: License :: OSI Approved :: MIT License
Classifier: Programming Language :: Python
Classifier: Programming Language :: Python :: 3
Requires-Python: >=3.5.0
Requires-Dist: numpy
Requires-Dist: python-constraint
Requires-Dist: matplotlib
Requires-Dist: pandas
Requires-Dist: openpyxl
Requires-Dist: python-dateutil
